{
  "version": "5.0.1",
  "flags": {},
  "shapes": [
    {
      "label": "motor 7",
      "points": [
        [
          476.4214555476167,
          39.48453608247423
        ],
        [
          427.22833520465485,
          -0.5983464325814261
        ]
      ],
      "group_id": null,
      "shape_type": "rectangle",
      "flags": {}
    },
    {
      "label": "s40_40_G 8",
      "points": [
        [
          563.841584158416,
          166.83168316831683
        ],
        [
          481.66336633663366,
          118.31683168316832
        ]
      ],
      "group_id": null,
      "shape_type": "rectangle",
      "flags": {}
    },
    {
      "label": "f20_20_G 9",
      "points": [
        [
          489.5841584158415,
          336.13861386138615
        ],
        [
          414.33663366336634,
          269.80198019801986
        ]
      ],
      "group_id": null,
      "shape_type": "rectangle",
      "flags": {}
    },
    {
      "label": "bearing 10",
      "points": [
        [
          253.0620499310362,
          334.7956634428453
        ],
        [
          283.78646524446253,
          363.9226293763399
        ]
      ],
      "group_id": null,
      "shape_type": "rectangle",
      "flags": {}
    },
    {
      "label": "m20_100 11",
      "points": [
        [
          96.01980198019803,
          243.56435643564356
        ],
        [
          143.09033377564558,
          327.32979483515356
        ]
      ],
      "group_id": null,
      "shape_type": "rectangle",
      "flags": {}
    },
    {
      "label": "axis 12",
      "points": [
        [
          80.55078085128099,
          80.30009186485657
        ],
        [
          147.87751352454828,
          114.95355721139121
        ]
      ],
      "group_id": null,
      "shape_type": "rectangle",
      "flags": {}
    }
  ],
  "imagePath": "frame0401.jpg",
  "imageData": null,
  "imageHeight": 480,
  "imageWidth": 640
}