{
  "version": "5.0.1",
  "flags": {},
  "shapes": [
    {
      "label": "axis 1",
      "points": [
        [
          238.25490196078437,
          296.07843137254906
        ],
        [
          274.5294117647059,
          369.60784313725486
        ]
      ],
      "group_id": null,
      "shape_type": "rectangle",
      "flags": {}
    },
    {
      "label": "m20_100 2",
      "points": [
        [
          443.156862745098,
          290.6862745098039
        ],
        [
          531.8823529411765,
          337.2549019607843
        ]
      ],
      "group_id": null,
      "shape_type": "rectangle",
      "flags": {}
    },
    {
      "label": "bearing 3",
      "points": [
        [
          528.9411764705883,
          171.56862745098044
        ],
        [
          557.8627450980391,
          198.52941176470594
        ]
      ],
      "group_id": null,
      "shape_type": "rectangle",
      "flags": {}
    },
    {
      "label": "f20_20_G 4",
      "points": [
        [
          466.68627450980387,
          22.549019607843114
        ],
        [
          519.1372549019607,
          74.01960784313725
        ]
      ],
      "group_id": null,
      "shape_type": "rectangle",
      "flags": {}
    },
    {
      "label": "m20 6",
      "points": [
        [
          93.64705882352942,
          163.23529411764704
        ],
        [
          120.11764705882354,
          137.2549019607843
        ]
      ],
      "group_id": null,
      "shape_type": "rectangle",
      "flags": {}
    },
    {
      "label": "motor 7",
      "points": [
        [
          216.19607843137254,
          35.78431372549019
        ],
        [
          170.1176470588235,
          -1.4313725490196099
        ]
      ],
      "group_id": null,
      "shape_type": "rectangle",
      "flags": {}
    }
  ],
  "imagePath": "frame0071.jpg",
  "imageData": null,
  "imageHeight": 480,
  "imageWidth": 640
}