{
  "version": "5.0.1",
  "flags": {},
  "shapes": [
    {
      "label": "axis 1",
      "points": [
        [
          453.45098039215685,
          241.1764705882353
        ],
        [
          520.1176470588233,
          297.5490196078433
        ]
      ],
      "group_id": null,
      "shape_type": "rectangle",
      "flags": {}
    },
    {
      "label": "m20_100 2",
      "points": [
        [
          534.8235294117645,
          66.17647058823532
        ],
        [
          567.1764705882352,
          136.76470588235298
        ]
      ],
      "group_id": null,
      "shape_type": "rectangle",
      "flags": {}
    },
    {
      "label": "bearing 3",
      "points": [
        [
          448.0588235294118,
          9.592326932761353e-14
        ],
        [
          475.5098039215686,
          25.490196078431374
        ]
      ],
      "group_id": null,
      "shape_type": "rectangle",
      "flags": {}
    },
    {
      "label": "m20 6",
      "points": [
        [
          205.90196078431373,
          333.82352941176464
        ],
        [
          234.82352941176472,
          302.4509803921569
        ]
      ],
      "group_id": null,
      "shape_type": "rectangle",
      "flags": {}
    },
    {
      "label": "motor 7",
      "points": [
        [
          140.70588235294116,
          189.7058823529412
        ],
        [
          75.50980392156863,
          150.00000000000003
        ]
      ],
      "group_id": null,
      "shape_type": "rectangle",
      "flags": {}
    },
    {
      "label": "s40_40_G 8",
      "points": [
        [
          206.88235294117646,
          63.235294117647065
        ],
        [
          136.56862745098042,
          1.9607843137254939
        ]
      ],
      "group_id": null,
      "shape_type": "rectangle",
      "flags": {}
    }
  ],
  "imagePath": "frame0144.jpg",
  "imageData": null,
  "imageHeight": 480,
  "imageWidth": 640
}