{
  "version": "5.0.1",
  "flags": {},
  "shapes": [
    {
      "label": "axis 1",
      "points": [
        [
          409.8235294117647,
          276.4705882352941
        ],
        [
          461.78431372549016,
          343.13725490196083
        ]
      ],
      "group_id": null,
      "shape_type": "rectangle",
      "flags": {}
    },
    {
      "label": "m20_100 2",
      "points": [
        [
          536.7843137254902,
          125.49019607843135
        ],
        [
          582.8627450980393,
          193.6274509803921
        ]
      ],
      "group_id": null,
      "shape_type": "rectangle",
      "flags": {}
    },
    {
      "label": "bearing 3",
      "points": [
        [
          488.2549019607844,
          36.27450980392166
        ],
        [
          515.7058823529412,
          61.76470588235294
        ]
      ],
      "group_id": null,
      "shape_type": "rectangle",
      "flags": {}
    },
    {
      "label": "m20 6",
      "points": [
        [
          151.00000000000003,
          298.03921568627464
        ],
        [
          178.94117647058826,
          269.60784313725503
        ]
      ],
      "group_id": null,
      "shape_type": "rectangle",
      "flags": {}
    },
    {
      "label": "motor 7",
      "points": [
        [
          142.6666666666666,
          136.76470588235316
        ],
        [
          80.41176470588232,
          101.47058823529413
        ]
      ],
      "group_id": null,
      "shape_type": "rectangle",
      "flags": {}
    },
    {
      "label": "s40_40_G 8",
      "points": [
        [
          241.19607843137254,
          37.254901960784316
        ],
        [
          191.1960784313725,
          -1.470588235294116
        ]
      ],
      "group_id": null,
      "shape_type": "rectangle",
      "flags": {}
    }
  ],
  "imagePath": "frame0124.jpg",
  "imageData": null,
  "imageHeight": 480,
  "imageWidth": 640
}